{
  "public_id": "drv_37bb01e653af",
  "driver": "Mad Stig",
  "summary": {
    "points": 11,
    "average_points_per_race": 11.0,
    "races": 1,
    "wins": 0,
    "podiums": 0,
    "average_finish": 5.0,
    "best_lap": "1:47.942",
    "best_lap_ms": 107942,
    "best_lap_track": "monza",
    "best_lap_car_model_id": 30,
    "best_lap_car_name_raw": "BMW M4 GT3",
    "best_lap_car_name": "BMW M4 GT3",
    "best_lap_session_type": "R",
    "penalty_count": 0,
    "penalty_points": 0,
    "fastest_lap_awards": 1,
    "most_raced_track": "monza",
    "last_race_at": "2026-03-18T01:29:13",
    "last_seen": "2026-03-18T01:29:13",
    "average_pace_ms": 111378,
    "average_pace": "1:51.378",
    "win_rate": 0.0,
    "podium_rate": 0.0,
    "average_positions_delta": null,
    "positions_delta_races": 0,
    "championship_rank": 868,
    "bestlap_rank": 370,
    "latest_changes": {
      "championship_rank": {
        "before": 867,
        "after": 868,
        "delta": 1,
        "trend": "down"
      }
    },
    "latest_change_at": "2026-03-29T00:48:39"
  },
  "recent_form": [
    5
  ],
  "track_stats": [
    {
      "track": "monza",
      "races": 1,
      "wins": 0,
      "podiums": 0,
      "points": 11,
      "finish_sum": 5,
      "average_finish": 5.0,
      "best_lap_ms": 107942,
      "best_lap": "1:47.942"
    }
  ],
  "race_history": [
    {
      "race_id": "260318_012913_R.json",
      "finished_at": "2026-03-18T01:29:13",
      "track": "monza",
      "car_model_id": 30,
      "car_name_raw": "BMW M4 GT3",
      "car_name": "BMW M4 GT3",
      "position": 5,
      "participants_count": 36,
      "winner": "Alexey Zhmachkin",
      "points": 11,
      "qualifying_position": null,
      "start_position": null,
      "start_position_source": "unknown",
      "positions_delta": null,
      "positions_gained": null,
      "positions_lost": null,
      "best_lap": "1:47.942",
      "best_lap_ms": 107942,
      "total_time": "20:31.121",
      "total_time_ms": 1231121,
      "gap": "0:22.203",
      "gap_ms": 22203,
      "lap_count": 11,
      "counted_for_stats": true,
      "had_best_lap": true,
      "penalty_count": 0,
      "penalty_points": 0,
      "changes": {
        "average_finish": {
          "before": null,
          "after": 5.0,
          "delta": null,
          "trend": "up"
        },
        "average_pace_ms": {
          "before": null,
          "after": 111378,
          "delta": null,
          "trend": "up"
        },
        "championship_rank": {
          "before": 1226,
          "after": 278,
          "delta": -948,
          "trend": "up"
        },
        "points": {
          "before": 0,
          "after": 11,
          "delta": 11,
          "trend": "up"
        },
        "races": {
          "before": 0,
          "after": 1,
          "delta": 1,
          "trend": "up"
        }
      },
      "rank_change": {
        "before": 1226,
        "after": 278,
        "delta": -948,
        "trend": "up"
      },
      "bestlap_rank_change": null
    }
  ],
  "penalties": {
    "penalty_count": 0,
    "penalty_points": 0,
    "reasons": {},
    "types": {}
  }
}